bctrl/__init__.py
bctrl-0.0.1.dist-info/METADATA
bctrl-0.0.1.dist-info/WHEEL
bctrl-0.0.1.dist-info/RECORD
