Metadata-Version: 2.4
Name: bctrl
Version: 0.0.1
Summary: Remote browser automation for AI agents - Python SDK
Project-URL: Homepage, https://github.com/bctrl/bctrl
Project-URL: Documentation, https://github.com/bctrl/bctrl#readme
Project-URL: Repository, https://github.com/bctrl/bctrl
Author: bctrl
License-Expression: ISC
Keywords: ai,automation,browser,playwright,puppeteer,scraping,selenium,web
Classifier: Development Status :: 1 - Planning
Classifier: Intended Audience :: Developers
Classifier: License :: OSI Approved :: ISC License (ISCL)
Classifier: Programming Language :: Python :: 3
Classifier: Programming Language :: Python :: 3.8
Classifier: Programming Language :: Python :: 3.9
Classifier: Programming Language :: Python :: 3.10
Classifier: Programming Language :: Python :: 3.11
Classifier: Programming Language :: Python :: 3.12
Classifier: Topic :: Internet :: WWW/HTTP :: Browsers
Classifier: Topic :: Software Development :: Libraries :: Python Modules
Requires-Python: >=3.8
